MANIFEST.in
README.md
README.rst
setup.py
./scripts/eval_stackimpute.py
./scripts/feature_process.py
./scripts/impute.py
./scripts/input_generation.py
./scripts/load_savemodel.py
./scripts/random_feature_top_selection.py
stackimpute/__init__.py
stackimpute/feature_process.py
stackimpute/metrics.py
stackimpute/model_structure.py
stackimpute/utils.py
stackimpute.egg-info/PKG-INFO
stackimpute.egg-info/SOURCES.txt
stackimpute.egg-info/dependency_links.txt
stackimpute.egg-info/requires.txt
stackimpute.egg-info/top_level.txt
stackimpute/data/__init__.py
stackimpute/data/input.tsv
stackimpute/data/input_NA.tsv
stackimpute/data/validation.tsv
stackimpute/data/validation_NA.tsv