Metadata-Version: 1.1
Name: stackimpute
Version: 0.0.1b0
Summary: stacking machine learning model for CpG methylation imputation
Home-page: https://github.com/sixone11/stackimpute
Author: Yi Liu
Author-email: yiliu11@zju.edu.cn
License: MIT
Keywords: machine learning,DNA methylation,imputation,stacking model
Platform: UNKNOWN
Classifier: Development Status :: 3 - Alpha
Classifier: Environment :: Console
Classifier: Intended Audience :: Science/Research
Classifier: License :: OSI Approved :: MIT License
Classifier: Natural Language :: English
Classifier: Programming Language :: Python :: 3.8
Classifier: Topic :: Scientific/Engineering :: Artificial Intelligence
Classifier: Topic :: Scientific/Engineering :: Bio-Informatics
